<?xml version="1.0" encoding="utf-8" ?>
<dwsync>
<file name="config.js" server="18.191.66.127//var/www/" local="132292373240000000" remote="132292373240000000" Dst="2" />
<file name="server_plugins.js" server="18.191.66.127//var/www/" local="132292373240000000" remote="132292373240000000" Dst="2" />
<file name="server_databases.js" server="18.191.66.127//var/www/" local="132292373240000000" remote="132292373240000000" Dst="2" />
<file name="db_query_generator.js" server="18.191.66.127//var/www/" local="132292373240000000" remote="132292373240000000" Dst="2" />
<file name="import.js" server="18.191.66.127//var/www/" local="132292373240000000" remote="132292373240000000" Dst="2" />
<file name="indexes.js" server="18.191.66.127//var/www/" local="132292373240000000" remote="132292373240000000" Dst="2" />
<file name="navigation.js" server="18.191.66.127//var/www/" local="132292373240000000" remote="132292373240000000" Dst="2" />
<file name="server_status_advisor.js" server="18.191.66.127//var/www/" local="132292373240000000" remote="132292373240000000" Dst="2" />
<file name="error_report.js" server="18.191.66.127//var/www/" local="132292373240000000" remote="132292373240000000" Dst="2" />
<file name="makegrid.js" server="18.191.66.127//var/www/" local="132292373240000000" remote="132292373240000000" Dst="2" />
<file name="functions.js" server="18.191.66.127//var/www/" local="132292373240000000" remote="132292373240000000" Dst="2" />
<file name="normalization.js" server="18.191.66.127//var/www/" local="132292373240000000" remote="132292373240000000" Dst="2" />
<file name="tbl_operations.js" server="18.191.66.127//var/www/" local="132292373240000000" remote="132292373240000000" Dst="2" />
<file name="db_operations.js" server="18.191.66.127//var/www/" local="132292373240000000" remote="132292373240000000" Dst="2" />
<file name="db_central_columns.js" server="18.191.66.127//var/www/" local="132292373240000000" remote="132292373240000000" Dst="2" />
<file name="server_status_sorter.js" server="18.191.66.127//var/www/" local="132292373240000000" remote="132292373240000000" Dst="2" />
<file name="db_multi_table_query.js" server="18.191.66.127//var/www/" local="132292373240000000" remote="132292373240000000" Dst="2" />
<file name="export_output.js" server="18.191.66.127//var/www/" local="132292373240000000" remote="132292373240000000" Dst="2" />
<file name="doclinks.js" server="18.191.66.127//var/www/" local="132292373240000000" remote="132292373240000000" Dst="2" />
<file name="db_search.js" server="18.191.66.127//var/www/" local="132292373240000000" remote="132292373240000000" Dst="2" />
<file name="microhistory.js" server="18.191.66.127//var/www/" local="132292373240000000" remote="132292373240000000" Dst="2" />
<file name="server_user_groups.js" server="18.191.66.127//var/www/" local="132292373240000000" remote="132292373240000000" Dst="2" />
<file name="server_privileges.js" server="18.191.66.127//var/www/" local="132292373240000000" remote="132292373240000000" Dst="2" />
<file name="tbl_change.js" server="18.191.66.127//var/www/" local="132292373240000000" remote="132292373240000000" Dst="2" />
<file name="tbl_chart.js" server="18.191.66.127//var/www/" local="132292373240000000" remote="132292373240000000" Dst="2" />
<file name="page_settings.js" server="18.191.66.127//var/www/" local="132292373240000000" remote="132292373240000000" Dst="2" />
<file name="rte.js" server="18.191.66.127//var/www/" local="132292373240000000" remote="132292373240000000" Dst="2" />
<file name="server_status_monitor.js" server="18.191.66.127//var/www/" local="132292373240000000" remote="132292373240000000" Dst="2" />
<file name="multi_column_sort.js" server="18.191.66.127//var/www/" local="132292373240000000" remote="132292373240000000" Dst="2" />
<file name="ajax.js" server="18.191.66.127//var/www/" local="132292373240000000" remote="132292373240000000" Dst="2" />
<file name="db_qbe.js" server="18.191.66.127//var/www/" local="132292373240000000" remote="132292373240000000" Dst="2" />
<file name="common.js" server="18.191.66.127//var/www/" local="132292373240000000" remote="132292373240000000" Dst="2" />
<file name="console.js" server="18.191.66.127//var/www/" local="132292373240000000" remote="132292373240000000" Dst="2" />
<file name="db_tracking.js" server="18.191.66.127//var/www/" local="132292373240000000" remote="132292373240000000" Dst="2" />
<file name="whitelist.php" server="18.191.66.127//var/www/" local="132292373240000000" remote="132292373240000000" Dst="2" />
<file name="tbl_relation.js" server="18.191.66.127//var/www/" local="132292373240000000" remote="132292373240000000" Dst="2" />
<file name="u2f.js" server="18.191.66.127//var/www/" local="132292373240000000" remote="132292373240000000" Dst="2" />
<file name="gis_data_editor.js" server="18.191.66.127//var/www/" local="132292373240000000" remote="132292373240000000" Dst="2" />
<file name="server_status_queries.js" server="18.191.66.127//var/www/" local="132292373240000000" remote="132292373240000000" Dst="2" />
<file name="export.js" server="18.191.66.127//var/www/" local="132292373240000000" remote="132292373240000000" Dst="2" />
<file name="tbl_select.js" server="18.191.66.127//var/www/" local="132292373240000000" remote="132292373240000000" Dst="2" />
<file name="tbl_tracking.js" server="18.191.66.127//var/www/" local="132292373240000000" remote="132292373240000000" Dst="2" />
<file name="db_structure.js" server="18.191.66.127//var/www/" local="132292373240000000" remote="132292373240000000" Dst="2" />
<file name="tbl_structure.js" server="18.191.66.127//var/www/" local="132292373240000000" remote="132292373240000000" Dst="2" />
<file name="server_status_variables.js" server="18.191.66.127//var/www/" local="132292373240000000" remote="132292373240000000" Dst="2" />
<file name="tbl_gis_visualization.js" server="18.191.66.127//var/www/" local="132292373240000000" remote="132292373240000000" Dst="2" />
<file name="keyhandler.js" server="18.191.66.127//var/www/" local="132292373240000000" remote="132292373240000000" Dst="2" />
<file name="tbl_find_replace.js" server="18.191.66.127//var/www/" local="132292373240000000" remote="132292373240000000" Dst="2" />
<file name="replication.js" server="18.191.66.127//var/www/" local="132292373240000000" remote="132292373240000000" Dst="2" />
<file name="messages.php" server="18.191.66.127//var/www/" local="132292373240000000" remote="132292373240000000" Dst="2" />
<file name="menu-resizer.js" server="18.191.66.127//var/www/" local="132292373240000000" remote="132292373240000000" Dst="2" />
<file name="chart.js" server="18.191.66.127//var/www/" local="132292373240000000" remote="132292373240000000" Dst="2" />
<file name="tbl_zoom_plot_jqplot.js" server="18.191.66.127//var/www/" local="132292373240000000" remote="132292373240000000" Dst="2" />
<file name="server_variables.js" server="18.191.66.127//var/www/" local="132292373240000000" remote="132292373240000000" Dst="2" />
<file name="cross_framing_protection.js" server="18.191.66.127//var/www/" local="132292373240000000" remote="132292373240000000" Dst="2" />
<file name="shortcuts_handler.js" server="18.191.66.127//var/www/" local="132292373240000000" remote="132292373240000000" Dst="2" />
<file name="server_status_processes.js" server="18.191.66.127//var/www/" local="132292373240000000" remote="132292373240000000" Dst="2" />
<file name="sql.js" server="18.191.66.127//var/www/" local="132292373240000000" remote="132292373240000000" Dst="2" />
</dwsync>